treehugger/__init__.py
treehugger/__main__.py
treehugger/data.py
treehugger/ec2.py
treehugger/kms.py
treehugger/messaging.py
treehugger/os_ext.py
treehugger/s3.py
treehugger/yaml.py
treehugger/cli/__init__.py
treehugger/cli/decrypt_file.py
treehugger/cli/edit.py
treehugger/cli/encrypt_file.py
treehugger/cli/execute.py
treehugger/cli/parser.py
treehugger/cli/print_out.py
treehugger/cli/utils.py
treehugger-3.0.0.dist-info/LICENSE.txt
treehugger-3.0.0.dist-info/METADATA
treehugger-3.0.0.dist-info/RECORD
treehugger-3.0.0.dist-info/WHEEL
treehugger-3.0.0.dist-info/entry_points.txt
treehugger-3.0.0.dist-info/top_level.txt
