Metadata-Version: 2.1
Name: treehugger
Version: 3.0.0
Summary: Securely manage runtime configuration
Home-page: https://github.com/timeoutdigital/treehugger
Author: Adam Johnson, Niklas Lindblad
Author-email: sysadmin@timeout.com
License: ISC License
Download-URL: https://github.com/timeoutdigital/treehugger/archive/3.0.0.tar.gz
Platform: UNKNOWN
Classifier: Development Status :: 5 - Production/Stable
Classifier: Intended Audience :: Developers
Classifier: License :: OSI Approved :: ISC License (ISCL)
Classifier: Natural Language :: English
Classifier: Programming Language :: Python :: 3.4
Classifier: Programming Language :: Python :: 3.5
Classifier: Programming Language :: Python :: 3.6
Requires-Python: >=3.4
Requires-Dist: boto3
Requires-Dist: PyYAML
Requires-Dist: requests
